algofins_broker_v2/__init__.py
algofins_broker_v2/algofins_broker_v2.py
algofins_broker_v2/cli.py
algofins_broker_v2-0.1.0.dist-info/licenses/AUTHORS.rst
algofins_broker_v2-0.1.0.dist-info/METADATA
algofins_broker_v2-0.1.0.dist-info/WHEEL
algofins_broker_v2-0.1.0.dist-info/top_level.txt
algofins_broker_v2-0.1.0.dist-info/RECORD
